LICENSE.md
README.md
pyproject.toml
src/sb_detectors/__init__.py
src/sb_detectors/detectors.py
src/sb_detectors.egg-info/PKG-INFO
src/sb_detectors.egg-info/SOURCES.txt
src/sb_detectors.egg-info/dependency_links.txt
src/sb_detectors.egg-info/requires.txt
src/sb_detectors.egg-info/top_level.txt
src/sb_detectors/tests/__init__.py
src/sb_detectors/tests/test_detectors.py